gf180mcu/__init__.py
gf180mcu/config.py
gf180mcu/layers.py
gf180mcu/layers.yaml
gf180mcu/tech.py
gf180mcu/cells/__init__.py
gf180mcu/cells/cap_mim.py
gf180mcu/cells/cap_mos.py
gf180mcu/cells/diode.py
gf180mcu/cells/fet.py
gf180mcu/cells/guardring.py
gf180mcu/cells/res.py
gf180mcu/cells/via_generator.py
gf180mcu/cells/waveguides.py
gf180mcu/klayout/gf180_x64.png
gf180mcu/klayout/grain.xml
gf180mcu/klayout/tech/gf180mcu.lyp
gf180mcu/klayout/tech/gf180mcu.lyt
gf180mcu/klayout/tech/gf180mcu.map
gf180mcu-0.4.0.dist-info/licenses/LICENSE
gf180mcu-0.4.0.dist-info/WHEEL
gf180mcu-0.4.0.dist-info/METADATA
gf180mcu-0.4.0.dist-info/RECORD
