Metadata-Version: 2.4
Name: gf180mcu
Version: 0.4.0
Summary: GlobalFoundries 180nm MCU
Keywords: python
Author-email: gdsfactory <contact@gdsfactory.com>
Requires-Python: >=3.11,<3.14
Classifier: Programming Language :: Python :: 3.11
Classifier: Programming Language :: Python :: 3.12
Classifier: Programming Language :: Python :: 3.13
Classifier: Operating System :: OS Independent
License-File: LICENSE
Requires-Dist: gdsfactory~=9.12.2
Requires-Dist: pre-commit ; extra == "dev"
Requires-Dist: pytest ; extra == "dev"
Requires-Dist: pytest-cov ; extra == "dev"
Requires-Dist: pytest_regressions ; extra == "dev"
Requires-Dist: pytest-github-actions-annotate-failures ; extra == "dev"
Requires-Dist: autodoc_pydantic ; extra == "docs"
Requires-Dist: jupytext ; extra == "docs"
Requires-Dist: jupyter-book>=0.15.1,<1.1 ; extra == "docs"
Requires-Dist: pytest ; extra == "tests"
Requires-Dist: pytest-cov ; extra == "tests"
Provides-Extra: dev
Provides-Extra: docs
Provides-Extra: tests
